coreplus/__init__.py
coreplus/configs.py
coreplus/urls.py
coreplus/version.py
coreplus/api/README.md
coreplus/api/__init__.py
coreplus/api/apps.py
coreplus/api/consts.py
coreplus/api/helpers.py
coreplus/api/schemas.py
coreplus/api/urls.py
coreplus/api/views.py
coreplus/api/endpoints/__init__.py
coreplus/api/endpoints/serializers.py
coreplus/api/endpoints/v1.py
coreplus/api/endpoints/v2.py
coreplus/api/locale/id/LC_MESSAGES/django.mo
coreplus/api/locale/id/LC_MESSAGES/django.po
coreplus/api/templates/drf_spectacular/redoc.html
coreplus/contacts/__init__.py
coreplus/contacts/abstracts.py
coreplus/contacts/admin.py
coreplus/contacts/apps.py
coreplus/contacts/gis.py
coreplus/contacts/inlines.py
coreplus/contacts/models.py
coreplus/contacts/api/__init__.py
coreplus/contacts/api/v1/__init__.py
coreplus/contacts/api/v1/serializers.py
coreplus/contacts/locale/id/LC_MESSAGES/django.mo
coreplus/contacts/locale/id/LC_MESSAGES/django.po
coreplus/contacts/management/__init__.py
coreplus/contacts/management/commands/__init__.py
coreplus/contacts/management/commands/populate_countries.py
coreplus/contacts/migrations/0001_initial.py
coreplus/contacts/migrations/0002_alter_billingaddress_address_and_more.py
coreplus/contacts/migrations/0003_billingaddress_district_deliverableaddress_district_and_more.py
coreplus/contacts/migrations/__init__.py
coreplus/docs/__init__.py
coreplus/docs/apps.py
coreplus/docs/urls.py
coreplus/docs/views.py
coreplus/docs/management/__init__.py
coreplus/docs/management/commands/__init__.py
coreplus/docs/management/commands/build_docs.py
coreplus/docs/templates/docs/_base_one.html
coreplus/docs/templates/docs/_base_two.html
coreplus/docs/templates/docs/index.html
coreplus/docs/tests/__init__.py
coreplus/docs/tests/runtests.py
coreplus/docs/tests/test_views.py
coreplus/docs/tests/urls.py
coreplus/docs/tests/test_docs/index.html
coreplus/docs/tests/test_docs/sub_dir/index.html
coreplus/hooks/README.md
coreplus/hooks/__init__.py
coreplus/hooks/admin.py
corepluslib-1.0.dist-info/LICENSE
corepluslib-1.0.dist-info/METADATA
corepluslib-1.0.dist-info/WHEEL
corepluslib-1.0.dist-info/top_level.txt
corepluslib-1.0.dist-info/RECORD
