Metadata-Version: 2.1
Name: corepluslib
Version: 1.0
Summary: Django functional modules
Home-page: https://github.com/motivactions/corepluslib
Author: Zero Plus
Author-email: sasri.works@gmail.com
License: MIT
Project-URL: Documentation, https://github.com/motivactions/corepluslib
Project-URL: Source, https://github.com/motivactions/corepluslib
Classifier: Environment :: Web Environment
Classifier: Framework :: Django
Classifier: Intended Audience :: Developers
Classifier: License :: OSI Approved :: MIT License
Classifier: Operating System :: OS Independent
Classifier: Programming Language :: Python
Classifier: Programming Language :: Python :: 3
Classifier: Programming Language :: Python :: 3 :: Only
Classifier: Programming Language :: Python :: 3.8
Classifier: Programming Language :: Python :: 3.9
Classifier: Topic :: Internet :: WWW/HTTP
Classifier: Topic :: Internet :: WWW/HTTP :: Dynamic Content
Classifier: Topic :: Internet :: WWW/HTTP :: WSGI
Classifier: Topic :: Software Development :: Libraries :: Python Modules
Classifier: Topic :: Software Development :: Libraries :: Application Frameworks
Requires-Python: >=3.8
License-File: LICENSE
Requires-Dist: django (<=4.3,>=4.2)
Requires-Dist: django-phonenumber-field
Requires-Dist: django-polymorphic
Requires-Dist: django-mptt
Requires-Dist: django-filter
Requires-Dist: drf-spectacular
Requires-Dist: drf-spectacular-sidecar
Requires-Dist: langdetect
Requires-Dist: easy-thumbnails
Requires-Dist: babel
Requires-Dist: bleach
Requires-Dist: boto3
Requires-Dist: mistune (<=2.0.4)
Requires-Dist: scikit-learn
Requires-Dist: phonenumbers
Requires-Dist: pillow
Requires-Dist: pycountry
Requires-Dist: qrcode
Requires-Dist: geopy
